{
  "users": [
    {
      "id": "bff3",
      "firstName": "Lance paul",
      "lastName": "Brown top",
      "email": "wumoles@mailinator.com",
      "age": "40",
      "addresses": [
        {
          "street": "Dolorum ex impedit ",
          "city": "Porro a est itaque ",
          "location": "Consequatur ad cillu"
        },
        {
          "street": "Inventore natus ratis",
          "city": "sdfsdfasdf",
          "location": "sadfasdfasdfasdf"
        },
        {
          "street": "sdfasdf",
          "city": "sdfsdfasd",
          "location": "sdfasfsdfa"
        },
        {
          "street": "Main Street Qazafi Colony Rahim yar khan",
          "city": "Rahim yar khan",
          "location": "Et quo tenetur conse"
        },
        {
          "street": "Main Street Muhallah Masten Shah Rahim Yar Khan",
          "city": "Rahim Yar Khan",
          "location": "Et quo tenetur conse"
        }
      ]
    },
    {
      "id": "fb3b",
      "firstName": "Hashim",
      "lastName": "Fischer",
      "email": "jicu@mailinator.com",
      "age": "28",
      "addresses": [
        {
          "street": "Sit eum ut dolores ",
          "city": "Eaque nisi eu volupt",
          "location": "Non repudiandae quas"
        },
        {
          "street": "Sint ad cupidatat ap",
          "city": "Porro a est itaque ",
          "location": "Fugiat dicta ullamco"
        }
      ]
    },
    {
      "id": "a0b1",
      "firstName": "Reagan",
      "lastName": "Gentry",
      "email": "mequpalos@mailinator.com",
      "age": "32",
      "addresses": [
        {
          "street": "Architecto quibusdam",
          "city": "Distinctio Iusto ul",
          "location": "Et quo tenetur conse"
        },
        {
          "street": "Main Street Qazafi Colony Rahim yar khan",
          "city": "Rahim yar khan",
          "location": "asdfasdfasdf"
        }
      ]
    },
    {
      "id": "e630",
      "firstName": "Adena",
      "lastName": "Booker",
      "email": "jiroxab@mailinator.com",
      "age": "66",
      "addresses": [
        {
          "street": "Non voluptate sed du",
          "city": "Excepturi mollit por",
          "location": "Ex minim molestiae c"
        },
        {
          "street": "Main Street Qazafi Colony Rahim yar khan",
          "city": "Birmingham",
          "location": "Dolor amet dolor do"
        },
        {
          "street": "Street No. 1 Main street Muhallah Mastan Shah",
          "city": "Rahim Yar khan",
          "location": "Ex minim molestiae c"
        }
      ]
    },
    {
      "id": "7fd9",
      "firstName": "September",
      "lastName": "Flores",
      "email": "pezufy@mailinator.com",
      "age": "30",
      "addresses": [
        {
          "street": "Tempora expedita obc",
          "city": "Est quasi qui vel t",
          "location": "Unde unde exercitati"
        }
      ]
    }
  ]
}